{
  "project_info": {
    "project_number": "669474853864",
    "firebase_url": "https://zett-2d69f-default-rtdb.firebaseio.com",
    "project_id": "zett-2d69f",
    "storage_bucket": "zett-2d69f.appspot.com"
  },
  "client": [
    {
      "client_info": {
        "mobilesdk_app_id": "1:669474853864:android:debb15d728efd335e44a5d",
        "android_client_info": {
          "package_name": "com.zett"
        }
      },
      "oauth_client": [
        {
          "client_id": "669474853864-l76flns2n4s2e6da17ue30i4634k0god.apps.googleusercontent.com",
          "client_type": 1,
          "android_info": {
            "package_name": "com.zett",
            "certificate_hash": "bf3222f2308c128222d4faab0db7f026c0e1e3a6"
          }
        },
        {
          "client_id": "669474853864-bfn4couikiufals96dsnj6thjnr40n6g.apps.googleusercontent.com",
          "client_type": 3
        }
      ],
      "api_key": [
        {
          "current_key": "AIzaSyCDEMglQvw0vEFepz12FTOj22PvPrB8z20"
        }
      ],
      "services": {
        "appinvite_service": {
          "other_platform_oauth_client": [
            {
              "client_id": "669474853864-bfn4couikiufals96dsnj6thjnr40n6g.apps.googleusercontent.com",
              "client_type": 3
            }
          ]
        }
      }
    }
  ],
  "configuration_version": "1"
}